ub/__init__.py
ub/tests/__init__.py
ub/tests/test_basic.py
ub-0.0.10.dist-info/LICENSE
ub-0.0.10.dist-info/METADATA
ub-0.0.10.dist-info/WHEEL
ub-0.0.10.dist-info/top_level.txt
ub-0.0.10.dist-info/RECORD
