Metadata-Version: 2.1
Name: ub
Version: 0.0.10
Summary: “UnBind” -- frees occupied ports by detecting and unbinding blocking processes
Home-page: https://github.com/ideaindirection/ub
License: mit
Keywords: port,unbind,free,processes
Platform: any
License-File: LICENSE
